django_softdelete/__about__.py
django_softdelete/__init__.py
django_softdelete/admin.py
django_softdelete/apps.py
django_softdelete/exceptions.py
django_softdelete/filters.py
django_softdelete/managers.py
django_softdelete/models.py
django_softdelete/signals.py
django_softdelete/migrations/__init__.py
django_softdelete/templates/admin/hard_delete_confirmation.html
django_softdelete/templates/admin/restore_confirmation.html
django_softdelete/templates/admin/soft_delete_confirmation.html
django_soft_delete-1.0.21.dist-info/METADATA
django_soft_delete-1.0.21.dist-info/WHEEL
django_soft_delete-1.0.21.dist-info/licenses/LICENSE
django_soft_delete-1.0.21.dist-info/RECORD
