Metadata-Version: 2.4
Name: django-soft-delete
Version: 1.0.21
Summary: Soft delete models, managers, queryset for Django
Project-URL: Homepage, https://github.com/san4ezy/django_softdelete
Author-email: Alexander Yudkin <san4ezy@gmail.com>
License-Expression: MIT
License-File: LICENSE
Classifier: Environment :: Web Environment
Classifier: Framework :: Django
Classifier: Intended Audience :: Developers
Classifier: Operating System :: OS Independent
Classifier: Programming Language :: Python
Classifier: Topic :: Software Development :: Libraries :: Python Modules
Requires-Python: >=3.6
Requires-Dist: django
